index_now/__init__.py
index_now/api_key.py
index_now/authentication.py
index_now/endpoint.py
index_now/py.typed
index_now/status_code.py
index_now/version.py
index_now/sitemap/__init__.py
index_now/sitemap/get.py
index_now/sitemap/parse.py
index_now/sitemap/submit.py
index_now/sitemap/filter/__init__.py
index_now/sitemap/filter/change_frequency.py
index_now/sitemap/filter/date_range.py
index_now/sitemap/filter/sitemap.py
index_now/url/__init__.py
index_now/url/submit.py
index_now_for_python-1.0.17.dist-info/licenses/LICENSE.md
index_now_for_python-1.0.17.dist-info/METADATA
index_now_for_python-1.0.17.dist-info/WHEEL
index_now_for_python-1.0.17.dist-info/top_level.txt
index_now_for_python-1.0.17.dist-info/RECORD
