Metadata-Version: 2.4
Name: index-now-for-python
Version: 1.0.17
Summary: Lightweight package that makes it easy to submit URLs to the IndexNow API of various search engines
Home-page: https://jakob-bagterp.github.io/index-now-for-python/
Download-URL: https://pypi.org/project/index-now-for-python/
Author: Jakob Bagterp
Author-email: jakob_bagterp@hotmail.com
Maintainer: Jakob Bagterp
Maintainer-email: jakob_bagterp@hotmail.com
License: MIT License
Project-URL: Bug Tracker, https://github.com/jakob-bagterp/index-now-for-python/issues
Project-URL: Documentation, https://jakob-bagterp.github.io/index-now-for-python/
Project-URL: API Reference, https://jakob-bagterp.github.io/index-now-for-python/reference/
Project-URL: Source Code, https://github.com/jakob-bagterp/index-now-for-python
Project-URL: Release Notes, https://github.com/jakob-bagterp/index-now-for-python/releases
Keywords: python,timer
Classifier: Programming Language :: Python :: 3
Classifier: Programming Language :: Python :: 3.11
Classifier: Programming Language :: Python :: 3.12
Classifier: Programming Language :: Python :: 3.13
Classifier: Programming Language :: Python :: 3.14
Classifier: License :: OSI Approved :: MIT License
Classifier: Operating System :: OS Independent
Requires-Python: >=3.11
License-File: LICENSE.md
Requires-Dist: colorist==1.8.10
Requires-Dist: lxml==6.0.2
Requires-Dist: requests==2.32.5
Provides-Extra: testing
Requires-Dist: coverage==7.13.1; extra == "testing"
Requires-Dist: flake8==7.3.0; extra == "testing"
Requires-Dist: mypy==1.19.0; extra == "testing"
Requires-Dist: pytest==9.0.2; extra == "testing"
Requires-Dist: pytest-cov==7.0.0; extra == "testing"
Requires-Dist: tox==4.32.0; extra == "testing"
Dynamic: download-url
Dynamic: license-file
